{
  "title": "路環公園跳島親子日：免費設施玩透透的經濟遊",
  "slug": "macau-attraction-guide-family-day-out-coloane-路環公園跳島親子日-免費設施玩透透的經濟遊-96620d",
  "industry": "attraction-guide",
  "category": "family-day-out",
  "area": "coloane",
  "url": "https://inari-kira-isla.github.io/macau-encyclopedia/articles/macau-attraction-guide-family-day-out-coloane-路環公園跳島親子日-免費設施玩透透的經濟遊-96620d.html",
  "published": "2026-04-11",
  "quality_score": 6.5,
  "word_count": 1648,
  "tags": [
    "路環親子遊",
    "免費景點",
    "澳門公園",
    "黑沙海灘",
    "經濟遊"
  ],
  "content": "## 路環：澳門價效比最高的家庭日出遊地\n\n作為持牌澳門導遊，我常被家長問：「帶孩子去澳門，有沒有不花大錢又能玩得盡興的地方？」答案肯定是路環。這個澳門最後的綠色角落，擁有全澳最完善的免費公共設施網路，從海灘到山頂、從自然步道到文化場館，一家人只需巴士車資就能享受完整的親子日。\n\n路環的地理優勢在於垂直分佈——海拔從0米的黑沙海灘到200多米的山頂公園，形成了層次豐富的遊玩空間。更重要的是，澳門政府在這裡投入了大量公共設施，全部免費開放，設施維護良好，安全措施完善。\n\n## 五大免費設施群：從海到山的完整體驗\n\n**1. 黑沙海灘設施群：澳門唯一的天然海灘體驗**\n\n黑沙海灘公園、黑沙海灘休憩區、黑沙海灘休閒中心三個設施相連，形成澳門最完整的海灘親子空間。孩子可以在天然黑沙上玩沙、戲水，家長在有遮蔭的休憩區看護。休閒中心提供乾淨的洗手間和淡水沖洗設施，比很多付費海灘的配套還完善。我建議上午9-11點來，這時海風不大，陽光溫和，最適合幼齡孩子。\n\n**地址：澳門路環新黑沙馬路 | 電話：+853 2833 7676**\n\n**2. 路環郊野公園：城市中的迷你叢林探險**\n\n這是澳門面積最大的郊野公園，步道系統完善，有適合推嬰兒車的平緩路線，也有讓大孩子消耗體力的山坡小徑。公園內的生態教育牌做得很用心，孩子可以邊走邊認識澳門本土植物。春季3-5月是最佳時節，山花盛開，溫度宜人。\n\n**地址：路環石排灣郊野公園徑 | 電話：+853 2888 0087**\n\n**3. 路環山頂公園：360度澳門全景免費看**\n\n很多人不知道澳門最美的全景觀景點是免費的。路環山頂公園視野開闊，可以看到澳門三島全貌，珠海橫琴也盡收眼底。下午4-6點是最佳拍照時間，逆光不強，景色層次分明。公園有涼亭和石凳，適合全家野餐。\n\n**地址：澳門路環高頂馬路Estrada do Alto de Coloane**\n\n**4. 路環市區文化館：免費的文化啟蒙空間**\n\n小而美的文化館，經常有兒童友善的展覽和工作坊。館內空調充足，是中午避暑的好去處。展品介紹路環漁村文化，孩子可以瞭解澳門的另一面。工作人員親切，樂意為小朋友講解。\n\n**地址：澳門路環計單奴街 | 電話：+853 2888 2279**\n\n**5. 棕櫚公園：市區中心的遊樂樞紐**\n\n路環市中心的小公園，雖然面積不大，但設施齊全，有兒童遊樂設施和成人健身器材。位置便利，是連線其他景點的中轉站。傍晚時分，本地居民帶小孩來玩，氛圍很生活化。\n\n**地址：路環棕櫚圓形地 | 電話：+853 2833 7676**\n\n## 實用資訊\n\n**交通：** 從澳門市區搭15、21A、25、26A號巴士直達路環市區，車程約30-40分鐘，車資MOP$ 6。建議購買澳門通卡，巴士費用MOP$ 3，一日內轉乘免費。\n\n**費用：** 所有設施免費開放，一家四口的總支出僅需巴士車資約MOP$ 24-48（視乎往返次數）。自備食物和水更經濟，路環市區也有平價茶餐廳可選。\n\n**開放時間：** 戶外設施全天開放，路環市區文化館週一至週日10:00-18:00（週三休館）。\n\n**最佳遊覽時間：** 4-6小時，建議上午9點出發，下午3點前結束戶外活動。\n\n## 旅遊小提示\n\n**路線規劃：** 建議按地勢由低到高遊玩——黑沙海灘(1.5小時) → 路環郊野公園(1小時) → 市區用餐及文化館(1小時) → 路環山頂公園(1小時)。這樣體力分配最合理。\n\n**裝備建議：** 防曬用品必備，路環紫外線較強。帶足飲水，山頂公園無販賣點。推嬰兒車的家庭選擇郊野公園的主步道，支路較陡。\n\n**安全注意：** 黑沙海灘無救生員駐守，家長需時刻看護幼童。山頂公園有懸崖區域，大風天避免前往。\n\n**當地人秘訣：** 週末上午10點前到黑沙海灘，可避開人潮。雨後的郊野公園空氣特別清新，但步道濕滑需小心。路環的日落是澳門最美的，時間充裕不妨在山頂公園等候。",
  "license": "CC BY 4.0"
}