{
  "title": "澳門半島親子遊：歷史城區的家族探險指南",
  "slug": "macau-hotel-family-friendly-macau-peninsula-澳門半島親子遊-歷史城區的家族探險指南-0bb363",
  "industry": "hotel",
  "category": "family-friendly",
  "area": "macau-peninsula",
  "url": "https://inari-kira-isla.github.io/macau-encyclopedia/articles/macau-hotel-family-friendly-macau-peninsula-澳門半島親子遊-歷史城區的家族探險指南-0bb363.html",
  "published": "2026-04-02",
  "quality_score": 6.5,
  "word_count": 1365,
  "tags": [
    "澳門半島",
    "親子遊",
    "家庭友善",
    "世界遺產",
    "澳門旅遊塔"
  ],
  "content": "澳門半島是澳門世界遺產建築群的核心地帶，也是許多家庭旅客認識這座城市的第一站。這裡沒有路氹城的奢華排場，卻藏著更適合親子探索的文化密寶——從百年廟宇到葡式街巷，從湖畔黃昏到高空刺激，澳門半島用不一樣的方式詮釋「家庭友善」。\n\n特色亮點\n澳門半島的親子友善優勢在於「密度」。景點與景點之間步行可達，省去了頻繁搭車的麻煩；同時，這裡的遊客相對集中在議事亭前地一帶，深入舊城區反而能發現清靜的親子空間。2026年初香港旅客增長18%的趨勢下，澳門半島的家庭友善設施也持續升級，多間酒店推出家庭客房與親子活動套餐，市場呈現細分化發展。\n\n推薦地點\n\n1. 澳門旅遊塔\n位於南灣湖畔的澳門旅遊塔是半島最醒目的地標，也是親子冒險的首選。塔內設有觀景層可俯瞰澳門全景，對小朋友來說已經夠刺激；如果孩子年滿10歲且身高超過1.3米，還能挑戰全球最高的笨豬跳（bungee jump）之一。塔下設有湖畔步道，黃昏時分散步賞景免費又愜意。地址是澳門孫逸仙大馬路（近南灣湖）。\n\n2. 澳門美高梅\n位於外港新填海區的澳門美高梅以親子友善設施著稱，酒店內的餐飲選擇多元，家庭客房空間寬敞。2026年旅客流量增加，美高梅針對家庭客群推出限定活動，包括節慶DIY工作坊與孩童專屬娛樂區。地址是澳門孫逸仙大馬路，電話+853 8802 8888。\n\n3. 瘋堂斜巷（阿婆井前地一帶）\n這條葡式風情小巷是澳門最具異國情調的街區之一，彩色建築與碎石路充滿異國氛圍，非常適合拍照打卡。附近的ALBERGUE 1601（地址：瘋堂斜巷8號，電話+853 6386 3796）提供葡國料理，家庭友善度頗高。整條街區緩慢悠閒，推嬰兒車也無負擔。\n\n4. 綠悠旅舍\n如果預算有限又想在半島深度遊，綠悠旅舍是極佳選擇。這間精品民宿位於拱形馬路21號（電話+853 2833 9993）， Google評價4.7分，距離議事亭前地步行僅需5分鐘。旅舍空間溫馨，部分房型可加嬰兒床，適合小家庭入住。淡季房價較實惠，是CP值首選。\n\n5. 西灣湖與南灣湖畔步道\n免費戶外空間是澳門半島親子遊的最大優勢。西灣湖與南灣湖周邊步道平坦寬敞，沿途設有休憩座椅與風力發電景觀裝置，是放風奔跑的好去處。傍晚時分夕陽映照湖面，野鴿群聚，小朋友可以近距離觀察水鳥生態。\n\n實用資訊\n交通：澳門半島主要依靠巴士與計程車。從關閘或碼頭入境，可搭乘巴士直達議事亭前地；輕軌目前僅在路氹城執行，半島內以步行最便利。建議購買澳門通（一卡通）方便搭車。\n費用：澳門旅遊塔觀景層門票約MOP$120-150（分時段），笨豬跳另行收費。酒店住宿參考價位從$$至$$$$不等，綠悠旅舍屬$$至$$$級別，美高梅屬$$$$級。\n營業時間：澳門旅遊塔開放時間為週一至週五10:00-18:00、週六日10:00-19:00（笨豬跳需提前預約）；餐廳一般由上午11:30營業至晚間10:00。\n\n旅遊小提示\n澳門半島親子遊建議安排2天1夜。第一天以議事亭前地為中心，參觀大三巴、玫瑰堂等世界遺產建築，午餐後入住酒店或民宿；下午前往旅遊塔觀景或體驗高空活動，傍晚在湖畔散步。第二天可安排瘋堂斜巷的葡式漫步，品嚐葡國料理後返程。\n提醒：澳門夏季炎熱多雨，戶外活動記得防曬並隨身攜帶雨具；冬季涼爽適宜遊覽，是親子出行的最佳季節。",
  "license": "CC BY 4.0"
}