{
  "title": "路氹城的澳門融合美食：從全球供應鏈看當代廚師的創新實驗",
  "slug": "macau-dining-macanese-fusion-cotai-路氹城的澳門融合美食-從全球供應鏈看當代廚師的創新實驗-e836b3",
  "industry": "dining",
  "category": "macanese-fusion",
  "area": "cotai",
  "url": "https://inari-kira-isla.github.io/macau-encyclopedia/articles/macau-dining-macanese-fusion-cotai-路氹城的澳門融合美食-從全球供應鏈看當代廚師的創新實驗-e836b3.html",
  "published": "2026-03-23",
  "quality_score": 7.5,
  "word_count": 2452,
  "tags": [
    "路氹城",
    "澳門融合美食",
    "Macanese Fusion",
    "Fine Dining",
    "度假村美食"
  ],
  "content": "**路氹城與澳門融合美食的新演變**\n\n如果說澳門半島代表了葡式美食的歷史沉澱，那麼路氹城（Cotai）就是澳門融合美食（Macanese Fusion）的實驗室。這個全球最大的綜合度假村叢集——威尼斯人、巴黎人、銀河、新濠影匯、永利皇宮、倫敦人六大旗艦矗立於此——每家度假村都配置10到20間不同級別的餐廳，從美食街到米芝蓮三星。這種密集的餐飲佈局創造了獨特的生態：一方面，頻繁流動的國際客源推動廚師大膽創新；另一方面，全球食材供應鏈的變動直接影響選單的實時調整。\n\n2026年春季，澳門融合美食正經歷一次無聲的轉向。美國牛隻存欄量創75年新低，全球牛肉供應緊張直接推動了路氹城廚師們的蛋白質多元化實驗。從傳統的葡式烤肉飯（Arroz de Pato），到融入本地海膽、帶子、北海道幹貝的當代詮釋，廚師們在限制中找到了創意出口。同時，隨著2026年FIFA世界盃在北美舉辦（6月11日至7月19日），賽事期間全球餐飲消費驟增，路氹城的餐廳開始推出區域融合主題套餐——南美燒烤風味的葡式海鮮飯、東南亞香料融入的澳門蜂蛋糕，甚至世界盃限定的雞尾酒配餐體驗。\n\n**路氹城Macanese Fusion的三層結構**\n\n與其他城市不同，路氹城的澳門融合美食分為三個清晰的層級，各有特色：\n\n**米芝蓮星級層級（Fine Dining Tier）**\n\n度假村駐點的米芝蓮星級餐廳是路氹城美食的金字塔頂。這些餐廳的主廚通常都擁有歐洲或亞洲米芝蓮背景，他們用澳門當地食材（尤其是珠江口的海鮮和廣東時令蔬菜）重新詮釋經典菜色。例如，用本地馬糞海膽替代歐洲海膽製作的膽醇奶凍、用澳門豬骨高湯完成的法式濃湯濃縮。這個層級的用餐費用通常在MOP$800至3,000人均（不含飲料），預訂需提前2至4週。這些餐廳會根據全球食材行情實時調整選單——當牛肉供應緊張時，他們轉向北海道和牛、澳洲草飼牛的稀缺部位，或索性強化海鮮與野禽菜色。\n\n**高階Casual Dining層級（Contemporary Fusion）**\n\n這個層級是路氹城最具活力的創新地帶。主廚們擁有更多的實驗自由度，將澳門傳統小食與國際烹飪技法混搭。經典案例包括：葡式蛋撻的現代變體（榛果餡、抹茶餡、黑蒜風味版本）、用分子料理手法詮釋的濃湯蝦餃、侵漬陳年威士忌的東坡肉配馬鈴薯泥。這層級人均消費MOP$200至600，走位較為彈性，多數可直接入場。特別是近年來，受到食材成本上升和全球乾旱威脅水資源的影響，餐廳開發出更多節水烹飪法（如低溫烹調、廢水再利用於醬料製作），同時增加植物性蛋白菜品，以應對牛肉短缺。\n\n**美食街與快式融合（Food Court Fusion）**\n\n度假村美食街聚集了10至15個品牌檔口，從傳統粥麵檔到創意漢堡、亞洲拌飯。這裡是體驗最純粹澳門融合精神的地方——廚師用30秒內的速度完成一碗融合碗麵（混搭葡式辣油、豉油、芝士碎的快手麵）。人均MOP$50至150，是測試廚師創意思維的最佳視窗。近期美食街的融合趨勢反映了全球成本壓力：更多選擇採用本地食材、減少冷鏈依賴，同時融入世界盃主題元素（如「阿根廷牛肉風味」名義下的本地牛肉替代品）。\n\n**如何識別值得嘗試的Macanese Fusion**\n\n在路氹城選擇餐廳時，有幾個實用的辨別標準：\n\n**選單新鮮度**：每月更新一次選單的餐廳說明主廚在積極應對食材變動；三個月或更久才更新選單的多是觀光餐廳。詢問「本月的特色菜」和「上月選單」的差異，認真的廚師會詳細解釋背後的食材故事。\n\n**主廚背景透明度**：米芝蓮星級餐廳應該在官方網站清楚標註主廚履歷和廚房哲學。如果找不到，多半是營銷重於實力的餐廳。\n\n**當地食材佔比**：詢問海鮮來源（應答「珠江口」或「澳門灣」而非泛指「亞洲」），蔬菜供應商（廣東時令為佳），調味料（自製或進口澳門牌）。融合美食的核心是「本地為底、國際為飾」。\n\n**價格與量的對應**：如果米芝蓮星級restaurant標價MOP$1,500人均卻提供12道小份量菜色，這是業界標準；若只有8道且份量明顯不足，可能遇上品質縮水。\n\n**實用旅遊資訊**\n\n**交通**：澳門輕軌（MRTmacao）路氹線直達各大度假村，車票MOP$6至8（單程）。若搭計程車從澳門半島到路氹城約需MOP$70至90（夜間加價50%）。度假村間有免費接駁巴士，持房卡或賭場會員卡可使用。\n\n**費用範圍總結**：\n- 米芝蓮星級：MOP$800至3,000人均\n- 高階Casual：MOP$200至600人均\n- 美食街：MOP$50至150人均\n- 飲料另計，葡萄酒加成通常100%至150%\n\n**預訂建議**：米芝蓮星級餐廳需提前2至4週線上預訂（大多支援OpenTable或官方網站），信用卡擔保。高階Casual多數無需預訂，但午餐12至1點和晚餐7至8點為高峰期。美食街全天無需等位。\n\n**營業時間**：多數餐廳遵循國際度假村標準——午餐11:30至14:30，下午茶14:30至17:30，晚餐18:00至23:00，某些米芝蓮星級提供21:30的第二輪晚餐檔。週末和賽事週末（世界盃期間）建議提前確認營業時間。\n\n**澳門融合美食的未來視角**\n\n路氹城的Macanese Fusion不是靜態的餐廳集合，而是動態回應全球食材與消費趨勢的活體。2026年的一大轉折是：全球牛肉危機推動了廚師對本地海鮮、植物蛋白和冷凍乾燥食材的深入研究。同時，西亞衝突導致的運輸成本上升，反而強化了「本地優先」的哲學——這個看似被動的限制，正在塑造澳門融合美食的新身份：不是複製歐洲或亞洲，而是建立一個基於珠江三角洲食材與全球烹飪方法論的獨有體系。\n\n最後，當你在路氹城某個度假村大廳的落地窗前，品嚐著一碗混搭葡式濃湯、廣東時令野菜、北海道帶子的「融合濃湯麵」時，你實際上在品嚐的不只是一道菜，而是這個時代澳門如何在全球化壓力與本地資源之間找到平衡的縮影。",
  "license": "CC BY 4.0"
}