{
  "title": "澳門半島新鮮食材供應鏈：從碼頭到餐桌的美食保鮮之旅",
  "slug": "macau-food-supply-cold-chain-logistics-macau-peninsula-澳門半島新鮮食材供應鏈-從碼頭到餐桌的美食保鮮之旅-1127a2",
  "industry": "food-supply",
  "category": "cold-chain-logistics",
  "area": "macau-peninsula",
  "url": "https://inari-kira-isla.github.io/macau-encyclopedia/articles/macau-food-supply-cold-chain-logistics-macau-peninsula-澳門半島新鮮食材供應鏈-從碼頭到餐桌的美食保鮮之旅-1127a2.html",
  "published": "2026-04-04",
  "quality_score": 7.5,
  "word_count": 1609,
  "tags": [
    "澳門美食",
    "食材採購",
    "市場導覽",
    "海鮮選購",
    "澳門半島"
  ],
  "content": "澳門半島作為東西文化交匯的美食之都，每天都有大量新鮮食材從世界各地運抵。這些珍貴的海鮮、肉類和進口蔬果能保持最佳狀態送達你的餐桌，背後仰賴的正是嚴密的冷鏈保鮮系統。對於重視食材品質的饕客來說，瞭解澳門的食材供應鏈不僅能幫你選到最新鮮的美食，更能深度體驗這座城市的美食文化。\n\n## 澳門半島食材保鮮特色\n\n澳門半島的地理位置決定了其獨特的食材供應模式。作為連線內地與海外的重要節點，這裡每天處理來自日本、澳洲、歐洲的空運海鮮，以及珠江三角洲的新鮮農產品。近期受中東局勢影響，全球冷鏈運輸成本上升約35%，但澳門的供應商透過最佳化配送路線和投資節能裝置，仍能確保食材品質。\n\n最值得關注的是澳門獨有的「雙溫區配送」系統。由於地域較小，配送商能在同一趟配送中處理不同溫度需求的食材，從-18°C的冰鮮海鮮到4°C的新鮮蔬果，效率遠超其他地區。\n\n## 精選食材體驗地點\n\n**十六浦綜合市場**\n位於內港的傳統濕貨市場，是體驗澳門食材供應鏈起點的最佳地點。這裡每天凌晨4點開始，就有來自珠海的蔬菜、順德的河鮮陸續到貨。市場內的冷藏設施雖然看似簡單，但溫控精準。最推薦早上7-9點前往，能看到攤販如何從保溫車中快速分揀食材，整個過程不超過15分鐘，確保冷鏈不斷。\n\n**新馬路海鮮街**\n這條街匯聚了十多家專業海鮮供應商，主要服務高檔餐廳。每家店都配備專業冷凍櫃，溫度控制在-2°C至2°C之間。老闆們會很自豪地展示他們的「冰鮮證書」—記錄海鮮從捕撈到店內的完整溫控歷程。建議下午2-4點造訪，這時剛好是歐洲空運海鮮到貨的時段。\n\n**三盞燈食材批發區**\n隱身在三盞燈圓形地周邊的幾家食材批發店，專門供應澳門餐廳界。這裡能找到日本A5和牛、法國鵝肝等頂級食材。店家會告訴你哪些食材是昨天空運到達，哪些需要預訂。價格比零售便宜20-30%，但通常要求最低購買量。\n\n**紅街市冷凍專區**\n位於紅街市三樓的冷凍食品專區，是本地家庭採購進口冷凍海鮮的首選。這裡的冷凍櫃24小時運轉，溫度穩定在-18°C。店家會根據解凍時間給出食用建議，比如挪威三文魚建議冷藏解凍12小時，阿根廷紅蝦只需6小時。\n\n**南灣湖景大馬路進口食材店**\n幾家專營進口食材的精品店，主要服務外籍居民和高檔餐廳。店內配備透明冷藏櫃，顧客能直接觀察食材儲存狀況。店員多數會說英語，能詳細解釋各種食材的儲存要求和最佳食用期限。\n\n## 實用資訊\n\n**交通方式**\n- 十六浦綜合市場：搭乘1、3、4號巴士至「十六浦」站\n- 新馬路海鮮街：搭乘2、5、7號巴士至「新馬路」站\n- 三盞燈區域：搭乘6、9、28B號巴士至「三盞燈」站\n- 紅街市：搭乘18、19號巴士至「紅街市」站\n- 南灣湖景大馬路：步行或搭乘計程車，起跳價MOP$19\n\n**最佳採購時間**\n- 濕貨市場：上午7:00-10:00（最新鮮）\n- 海鮮店：下午2:00-5:00（空運貨到貨）\n- 冷凍專區：全天營業，但建議避開午餐時間\n- 進口食材店：上午10:00-下午6:00\n\n**價格範圍**\n由於全球冷鏈成本上升，高檔海鮮價格較去年同期上漲15-25%。本地蔬果價格相對穩定，進口冷凍食品價格上漲約10%。\n\n## 選購小貼士\n\n觀察冷藏裝置是判斷商家專業度的關鍵。正規供應商的冷櫃都會顯示溫度，且有備用電源。詢問食材到貨時間，通常早上到貨的比下午到貨的更新鮮。\n\n選購海鮮時，注意觀察魚眼是否清澈、魚鰓是否鮮紅，這比依賴儲存時間更可靠。冷凍食品要檢查包裝是否有冰晶，過多冰晶表示可能經歷過溫度波動。\n\n購買進口食材時，索要儲存建議卡片，上面通常標註了最適合的解凍和烹調方式。許多店家還會提供WhatsApp聯絡方式，方便預訂稀有食材。\n\n最重要的是建立與供應商的信任關係。熟客往往能獲得新到貨食材的優先選購權，以及專業的烹調建議。在澳門這樣的小城市，口碑就是最好的品質保證。",
  "license": "CC BY 4.0"
}