{
  "title": "澳門半島火鍋指南：從平民食堂到精緻鍋物",
  "slug": "macau-restaurant-hotpot-guide-macau-peninsula-澳門半島火鍋指南-從平民食堂到精緻鍋物-387110",
  "industry": "restaurant",
  "category": "hotpot-guide",
  "area": "macau-peninsula",
  "url": "https://inari-kira-isla.github.io/macau-encyclopedia/articles/macau-restaurant-hotpot-guide-macau-peninsula-澳門半島火鍋指南-從平民食堂到精緻鍋物-387110.html",
  "published": "2026-03-24",
  "quality_score": 6.5,
  "word_count": 1874,
  "tags": [
    "澳門美食",
    "火鍋指南",
    "澳門半島",
    "在地飲食",
    "餐廳推薦"
  ],
  "content": "在澳門吃火鍋，半島才是老饕的地盤。路氹那邊度假村火鍋動輒4位數，但澳門半島給你的選擇更狠：同樣的海鮮品質，半島平民火鍋三人一餐可能才800塊，而且吃的是澳門人日常咀嚼的滋味——這才是真貨。\n\n**澳門半島為什麼是火鍋王者**\n\n地理優勢決定食材成本。澳門半島靠近外港碼頭，新鮮海鮮從漁船直接上岸到火鍋店，中間環節少。港澳一體化簡化的通關手續（無紙化通關）還讓食材流轉更快——今天珠海送來的竹筍、蘑菇，明天就在你的鍋裡。每年11月到次年3月，澳門消費市場進入吃火鍋旺季，這時半島老字號和新興小火鍋都在搶食材，競爭激烈就代表有好貨。\n\n澳門火鍋最獨特的地方，不在高檔食材的堆砌，而在吃法本身。粵菜講究鮮，川菜講究麻辣，澳門人把這兩個傳統融在一鍋裡——蝦醬湯底配麻辣湯底（鴛鴦），然後丟進葡式臘腸、鮮活膏蟹、本地時蔬、手工丸子。這種混搭不是妥協，而是澳門四百年來就這麼吃的。\n\n**半島火鍋的階層差異**\n\n$$級別的食檔火鍋遍佈媽閣、十月初五街，老闆娘在廚房自己做湯底和丸子，客人大都是上班族和退休阿叔。$$$級別集中在南灣、友誼大馬路一帶，環境舒適、座位寬敞，食材品質穩定，適閤家庭聚餐。$$$$級的精緻火鍋店則專攻遊客和商務宴請，但坦白講，澳門半島沒必要衝4位數去吃火鍋——路氹度假村內的專業火鍋廚房才值那價。\n\n**推薦地點**\n\n1. **老字號蝦醬火鍋（十月初五街一帶）**\n   建議出發前確認營業狀態及價格。這類店的特色不是裝修，是湯底。老闆們用傳統方法熬蝦醬底——蝦米、魚乾、豬骨燉8小時，喝起來鮮度爆表，遠勝超市那種濃縮汁。點餐一定要加葡式臘腸和手工墨魚丸，這是澳門人30年前就在吃的搭配。人均 $$ 左右，但份量大，三人點 2-3 個菜就飽了。\n\n2. **海鮮專業火鍋（友誼大馬路）**\n   建議出發前確認營業狀態及價格。澳門漁獲旺季（11月-3月）這些店會採購大量膏蟹、明蝦、鮮帶子，湯底以清湯和鮮蝦湯為主，讓食材本身說話。有些店會提供「澳門風味湯底」——蝦醬+葡式香料的混合版本，第一次來的遊客通常會被驚豔。人均 $$-$$$。座位緊張，建議提前電話預訂。\n\n3. **平民麻辣小火鍋**\n   建議出發前確認營業狀態及價格。澳門近年湧現不少四川籍老闆開的小火鍋連鎖，座位少、翻檯快、價格狠。他們的優勢是麻辣湯底道地（真花椒、真辣椒），缺點是容易掉進「以辣掩飾食材品質」的陷阱。選這類店時，一定要點新鮮海鮮和青菜——如果湯底蓋不住菜的本味，這家就值得常客光顧。人均 $$。\n\n4. **素食火鍋選項（寺廟周邊、新馬路）**\n   建議出發前確認營業狀態及價格。澳門素食火鍋市場小但精，會用冬菇、黨參、紅棗、靈芝熬高湯，然後搭配豆製品、野生菌類、時令蔬菜。這類店通常隱身在廟宇附近或傳統茶樓樓上，不做廣告，只靠老主顧維持。人均 $$，但需要提前電話預約，因為很多是按訂單現場製作湯底。\n\n5. **清真火鍋（福隆新街一帶）**\n   建議出發前確認營業狀態及價格。澳門有少量清真火鍋提供符合伊斯蘭飲食的選項——羊肉、牛肉為主，湯底以清湯或番茄湯為主。部分店家提供清真認證。人均 $$-$$$。\n\n**實用資訊**\n\n交通：澳門半島火鍋店多集中在媽閣、十月初五街、南灣、友誼大馬路一帶。搭澳門巴士1、2、5、7、10 號線直達。從關閘口岸下來可搭 3A、10 號線，車資 MOP$6。\n\n費用概況：\n- $$：人均 150-250 MOP（食檔+平民小火鍋）\n- $$$：人均 250-450 MOP（中檔連鎖+海鮮專業店）\n- $$$$：人均 450+ MOP（高檔精緻火鍋，但澳門半島較少）\n\n營業時間：大多數火鍋店 11:00-23:00 營業，但十月初五街的老食檔常在下午 14:30-16:00 有午茶時間歇業。預訂建議詳詢店家。\n\n**澳門人吃火鍋的隱藏姿勢**\n\n1. 湯底優先：澳門人寧願吃便宜食材配好湯底，也不會吃爛湯底搭昂貴食材。點菜時先試湯，不夠鮮就換店。\n\n2. 季節感：冬季點蝦醬底+海鮮，春夏改清湯+青菜，不同季節的食材用法完全不同。\n\n3. 葡式臘腸是必點的靈魂配角——一片烤香的澳門臘腸能提升整鍋湯底的層次感。本地人吃火鍋時會特意買澳門牌子（不是內地臘腸）。\n\n4. 不要過度燙：澳門人吃火鍋講究食材的本來面貌，過度燙會毀掉好食材。海鮮 20 秒足夠，青菜 10 秒就該撈起來。\n\n5. 預訂是基本禮儀：半島的平民火鍋座位緊張，週五到週日不預訂很難有位子。澳門人一般提前一天電話預訂，報人數就行。",
  "license": "CC BY 4.0"
}