{
  "title": "澳門半島南部尋寶攻略：南灣與西灣湖的平價小眾之選",
  "slug": "macau-shopping-guide-bargain-hunting-macau-peninsula-澳門半島南部尋寶攻略-南灣與西灣湖的平價小眾之選-d68ee2",
  "industry": "shopping-guide",
  "category": "bargain-hunting",
  "area": "macau-peninsula",
  "url": "https://inari-kira-isla.github.io/macau-encyclopedia/articles/macau-shopping-guide-bargain-hunting-macau-peninsula-澳門半島南部尋寶攻略-南灣與西灣湖的平價小眾之選-d68ee2.html",
  "published": "2026-04-02",
  "quality_score": 6.5,
  "word_count": 1536,
  "tags": [
    "澳門購物",
    "澳門半島",
    "南灣湖",
    "西灣湖",
    "平價購物"
  ],
  "content": "說起澳門購物，多數人直覺想到大三巴的手信街或路氹的免稅店，但其實澳門半島南部藏著許多在地人才知道的平價好去處。這裡遠離旅遊區的喧鬧，價格更親民，選擇也更接地氣。\n\n南灣湖與西灣湖一帶是澳門半島難得的悠閒購物區。與其去人擠人的大三巴，不如把腳步放慢，在這個充滿水岸風情的區域挖掘屬於你的寶物。\n\n**南灣湖商業步行區**是近年悄悄崛起的購物新地點。這裡原本是湖畔休憩區，近年多了幾家特色小店進駐，形成小型文創聚落。傍晚時分沿著湖邊步道散步，涼風吹來，非常舒服。\n\n步行區內的**Lakeview Craft**是少數結合在地設計與合理價位的選物店。店主從各地搜羅有趣的生活小物，包括澳門本地設計師的明信片（每張MOP$15起）、小型手工藝品（約MOP$50-120）。店內氛圍溫馨，店主親切得像朋友，願意分享哪些伴手禮送人最體面。\n\n順著湖畔走，**南灣手作市集**通常在週末下午舉辦（僅六日，MOP$10-18開放）。這裡聚集了澳門本地手作者，飾品、編織物、手工皂都有。價格自然比連鎖店划算，平均單品落在MOP$30-80之間。重點是這些都是獨一無二的手作，送禮自用兩相宜。\n\n距離南灣湖約十分鐘步程的**下環街市**是另一個不能錯過的挖寶點。街市二樓設有熟食中心，當地阿婆在這裡賣傳統餅食超過三十年。杏仁餅（MOP$35/袋）、蛋卷（MOP$45/盒）都是手工製，保質期約兩週。跟在遊客區的連鎖店比起來，這裡價格起碼便宜兩成，品質完全不輸。\n\n街市附近的**李康記海味**是識途老馬的秘密基地。這家老店專賣乾貨海味，店主是澳門本地人，會用不太標準的廣東話跟你解說花膠、瑤柱的分級。買來送長輩特別體面，自己拿來煮湯也划算。花膠最便宜的等級約MOP$150/兩，瑤柱MOP$80/斤都比市區大型藥房便宜。\n\n說到澳門的地標建築，**澳門旅遊塔**周邊也有值得一逛的商店。旅遊塔底部的紀念品店（MOP$50-300）比金光大道度假村內的便宜不少，而且款式較為傳統旅客風格。如果想找更具設計感的澳門紀念品，塔旁邊的**Craft Macau**是更好的選擇，這裡主打澳門設計師品牌，價格落在MOP$80-250之間，質感好很多。\n\n旅遊塔附近的**新口岸區**近年開了不少小型選物店，主要集中在星皓廣場一帶。**星光生活雜貨**主打北歐風格生活用品，價格比同型別香港店鋪便宜約三成。澳門居民經常來這裡買日常小物當伴手禮，實用又有品味。\n\n如果時間允許，傍晚時分建議先去西灣湖散步賞夕陽，然後沿著湖邊慢慢逛回南灣。這個路線不走回頭路，還能趁傍晚店家打烊前撿到尾聲折扣。澳門夏秋交替之際最宜購物，天氣舒適，店鋪優惠也開始多了。\n\n**實用資訊：**\n\n交通方面，從澳門半島市區前往南灣，可乘10A、10B巴士（票價MOP$6），在「南灣湖」站下達。自駕的話，湖邊有收費停車場（每小時MOP$15）。\n\n手信價格參考：杏仁餅MOP$35-50/袋、蛋卷MOP$45-60/盒、花膠MOP$150-300/兩、瑤柱MOP$80-150/斤。\n\n營業時間多數店鋪朝十晚七，街市熟食中心通常到下午三點就打烊，手作市集僅週末開放。旅遊塔商店營業至晚上九點。\n\n**旅遊小提示：**\n\n澳門半島南部適合安排在半日遊行程裡，建議下午三點到達，先逛手作市集或特色小店，傍晚賞西灣湖夕陽，晚上在旅遊塔用晚餐看夜景。全程用走的就能完成，不用另外搭車。\n\n這裡的店鋪多數規模小，支付方式以現金為主，準備三五百塊澳門幣現鈔最穩當。另外，澳門幣和港幣通用，但找續時常拿回港幣，用不完的話機場免稅店可以花掉。\n\n避開週末下午兩點到四點的人潮，那時手作市集最擁擠。週中下午去反而能從容逛，店主也更有時間陪你聊天。",
  "license": "CC BY 4.0"
}